houlang/__init__.py
houlang/binarization/unet_binarizer.py
houlang/lib/__init__.py
houlang/lib/test.py
houlang/lib/utils.py
houlang/lib/data/__init__.py
houlang/lib/data/annotations.py
houlang/lib/data/images.py
houlang/lib/data/parsers.py
houlang/reading_order/heuristic_reading_order_classifier.py
houlang/recognition/kraken_recognizer.py
houlang/recognition/meltingpot.mlmodel
houlang/segmentation/__init__.py
houlang/segmentation/yolo_segmenter.py
houlang/segmentation/yolov8n_lineseg.pt
houlang-0.0.6.dist-info/METADATA
houlang-0.0.6.dist-info/WHEEL
houlang-0.0.6.dist-info/top_level.txt
houlang-0.0.6.dist-info/RECORD
